[
  {
    "name": "Земельное право",
    "description": "Комплексная дисциплина, изучающая правовое регулирование земельных отношений в РФ, включая собственность, сделки, аренду, охрану земель и государственное управление",
    "topics": [
      {
        "name": "Охрана земель и экологические требования",
        "lectures": [
          {
            "title": "Экологические стандарты при использовании земли",
            "content": "### Принцип экологической безопасности\n\nСогласно **ст. 1 ЗК РФ**, при использовании земли необходимо соблюдать требования **охраны окружающей среды**. Это означает:\n\n1. **Недопущение загрязнения** — земля не должна быть загрязнена вредными веществами\n2. **Сохранение плодородия** — для сельскохозяйственных земель\n3. **Защита биоразнообразия** — сохранение естественных экосистем\n4. **Соблюдение санитарных норм** — расстояния от жилья, предприятий\n\n### Виды загрязнения\n\n- **Химическое** — удобрения, пестициды, промышленные отходы\n- **Радиационное** — радиоактивные вещества (ст. 42 Конституции РФ)\n- **Биологическое** — микроорганизмы, патогены\n- **Механическое** — строительный мусор, отходы\n\n### Ответственность\n\nЛица, виновные в загрязнении, несут ответственность согласно **ст. 254 ЗК РФ**.",
            "test": {
              "title": "Тест: Экологические стандарты",
              "timeLimit": 90,
              "questions": [
                {
                  "text": "Какие основные экологические требования установлены ст. 1 ЗК РФ?",
                  "difficulty": 1,
                  "isMultipleChoice": true,
                  "answers": [
                    { "text": "Охрана окружающей среды", "isCorrect": true },
                    { "text": "Сохранение плодородия", "isCorrect": true },
                    { "text": "Защита биоразнообразия", "isCorrect": true },
                    { "text": "Максимальная прибыль", "isCorrect": false }
                  ]
                },
                {
                  "text": "Какие виды загрязнения земли выделяют?",
                  "difficulty": 2,
                  "isMultipleChoice": true,
                  "answers": [
                    { "text": "Химическое", "isCorrect": true },
                    { "text": "Радиационное", "isCorrect": true },
                    { "text": "Биологическое", "isCorrect": true },
                    { "text": "Только промышленное", "isCorrect": false }
                  ]
                },
                {
                  "text": "Кто несет ответственность за загрязнение земли согласно ст. 254 ЗК РФ?",
                  "difficulty": 1,
                  "isMultipleChoice": false,
                  "answers": [
                    { "text": "Лица, виновные в загрязнении", "isCorrect": true },
                    { "text": "Только государство", "isCorrect": false },
                    { "text": "Соседи загрязненного участка", "isCorrect": false }
                  ]
                }
              ]
            }
          },
          {
            "title": "Санитарные и защитные зоны",
            "content": "### Определение защитных зон\n\nЗащитные зоны согласно **ст. 95 ЗК РФ** — это **полосы земли** вокруг объектов, где использование земли **ограничено**.\n\n### Виды защитных зон\n\n1. **Около промышленных объектов**\n   - Минимальное расстояние от жилых домов\n   - Устанавливаются в расчётах по экологии\n\n2. **Санитарные зоны водных объектов**\n   - От берега до 50-100 м\n   - Запрет на строительство\n\n3. **Лесные защитные полосы**\n   - Вокруг водоёмов\n   - Вдоль дорог\n\n4. **Около ЛЭП и коммуникаций**\n   - Минимум 5-10 м от линий электропередачи\n   - Запрет на строительство высоких объектов\n\n### Последствия нарушения\n\nСтроительство или использование в защитной зоне влечёт:\n- Снос объекта (ст. 222 ГК РФ)\n- Штрафы\n- Возмещение убытков",
            "test": {
              "title": "Тест: Защитные зоны",
              "timeLimit": 90,
              "questions": [
                {
                  "text": "Что такое защитная зона согласно ст. 95 ЗК РФ?",
                  "difficulty": 1,
                  "isMultipleChoice": false,
                  "answers": [
                    { "text": "Полоса земли, где использование ограничено для защиты объектов или населения", "isCorrect": true },
                    { "text": "Любой участок земли", "isCorrect": false },
                    { "text": "Только парки и скверы", "isCorrect": false }
                  ]
                },
                {
                  "text": "Какие виды защитных зон существуют?",
                  "difficulty": 2,
                  "isMultipleChoice": true,
                  "answers": [
                    { "text": "Около промышленных объектов", "isCorrect": true },
                    { "text": "Санитарные зоны водных объектов", "isCorrect": true },
                    { "text": "Около ЛЭП и коммуникаций", "isCorrect": true },
                    { "text": "Вокруг каждого дома", "isCorrect": false }
                  ]
                },
                {
                  "text": "Какое минимальное расстояние от берега водоёма устанавливается санитарная зона?",
                  "difficulty": 2,
                  "isMultipleChoice": false,
                  "answers": [
                    { "text": "50-100 метров", "isCorrect": true },
                    { "text": "10 метров", "isCorrect": false },
                    { "text": "Нет ограничений", "isCorrect": false }
                  ]
                }
              ]
            }
          },
          {
            "title": "Мелиорация и рекультивация земель",
            "content": "### Мелиорация земель\n\nМелиорация согласно **ст. 79 ЗК РФ** — это **улучшение земель путём инженерных работ**:\n\n#### Виды мелиорации\n\n1. **Гидромелиорация**\n   - Осушение переувлажнённых земель\n   - Орошение засушливых земель\n   - Регулирование уровня грунтовых вод\n\n2. **Химическая мелиорация**\n   - Известкование кислых почв\n   - Гипсование солёных земель\n   - Внесение удобрений\n\n3. **Механическая мелиорация**\n   - Выравнивание рельефа\n   - Расчистка от камней и корней\n   - Дренирование\n\n### Рекультивация\n\nРекультивация согласно **ст. 67 ЗК РФ** — это **восстановление нарушенных земель** после добычи, строительства:\n- Восстановление плодородия\n- Формирование нового ландшафта\n- Посадка растительности\n\n### Финансирование\n\nМелиорация финансируется из:\n- Бюджетов (государство)\n- Собственных средств пользователя\n- Инвестиций",
            "test": {
              "title": "Тест: Мелиорация и рекультивация",
              "timeLimit": 90,
              "questions": [
                {
                  "text": "Что такое мелиорация земель согласно ст. 79 ЗК РФ?",
                  "difficulty": 1,
                  "isMultipleChoice": false,
                  "answers": [
                    { "text": "Улучшение земель путём инженерных работ", "isCorrect": true },
                    { "text": "Продажа земли", "isCorrect": false },
                    { "text": "Только посадка деревьев", "isCorrect": false }
                  ]
                },
                {
                  "text": "Какие виды мелиорации существуют?",
                  "difficulty": 2,
                  "isMultipleChoice": true,
                  "answers": [
                    { "text": "Гидромелиорация", "isCorrect": true },
                    { "text": "Химическая мелиорация", "isCorrect": true },
                    { "text": "Механическая мелиорация", "isCorrect": true },
                    { "text": "Только орошение", "isCorrect": false }
                  ]
                },
                {
                  "text": "Что такое рекультивация земель согласно ст. 67 ЗК РФ?",
                  "difficulty": 1,
                  "isMultipleChoice": false,
                  "answers": [
                    { "text": "Восстановление нарушенных земель", "isCorrect": true },
                    { "text": "Изменение назначения земли", "isCorrect": false },
                    { "text": "Только уборка земли", "isCorrect": false }
                  ]
                }
              ]
            }
          },
          {
            "title": "Санитарно-защитные требования и ответственность",
            "content": "### Санитарно-защитные требования\n\nСогласно **ст. 42 Конституции РФ** и **ст. 254-256 ЗК РФ**, каждый имеет право на благоприятную окружающую среду.\n\n### Обязанности собственников\n\n1. **Не загрязнять** участок и соседние земли\n2. **Не вредить** подземным водам\n3. **Соблюдать расстояния** (СНиП, ГОСТы)\n4. **Содержать в чистоте** территорию\n5. **Убирать отходы** в соответствии с законом\n\n### Виды ответственности\n\n#### Административная\n- **ст. 8.1-8.6 КоАП РФ** — нарушения природопользования\n- Штрафы: 1,000—100,000 руб.\n\n#### Уголовная\n- **ст. 254 УК РФ** — загрязнение земли\n- Штрафы, исправительные работы, лишение свободы\n\n#### Гражданская\n- **ст. 1064 ГК РФ** — возмещение убытков\n- Возмещение вреда окружающей среде",
            "test": {
              "title": "Тест: Санитарные требования и ответственность",
              "timeLimit": 90,
              "questions": [
                {
                  "text": "Какие основные обязанности собственников земли согласно ст. 254-256 ЗК РФ?",
                  "difficulty": 2,
                  "isMultipleChoice": true,
                  "answers": [
                    { "text": "Не загрязнять участок", "isCorrect": true },
                    { "text": "Не вредить подземным водам", "isCorrect": true },
                    { "text": "Соблюдать санитарные расстояния", "isCorrect": true },
                    { "text": "Платить соседям", "isCorrect": false }
                  ]
                },
                {
                  "text": "Какие виды ответственности за нарушения установлены?",
                  "difficulty": 2,
                  "isMultipleChoice": true,
                  "answers": [
                    { "text": "Административная", "isCorrect": true },
                    { "text": "Уголовная", "isCorrect": true },
                    { "text": "Гражданская", "isCorrect": true },
                    { "text": "Только устное замечание", "isCorrect": false }
                  ]
                },
                {
                  "text": "Какой закон устанавливает штрафы за нарушения природопользования?",
                  "difficulty": 2,
                  "isMultipleChoice": false,
                  "answers": [
                    { "text": "Кодекс об административных правонарушениях (КоАП РФ) ст. 8.1-8.6", "isCorrect": true },
                    { "text": "Уголовный кодекс", "isCorrect": false },
                    { "text": "Гражданский процессуальный кодекс", "isCorrect": false }
                  ]
                }
              ]
            }
          }
        ],
        "test": {
          "title": "Итоговый тест: Охрана земель",
          "timeLimit": 420,
          "questions": [
            {
              "text": "Какой основной принцип охраны земли установлен ст. 1 ЗК РФ?",
              "difficulty": 1,
              "isMultipleChoice": false,
              "answers": [
                { "text": "Необходимо соблюдать требования охраны окружающей среды", "isCorrect": true },
                { "text": "Земля может использоваться без ограничений", "isCorrect": false },
                { "text": "Охрана только за государством", "isCorrect": false }
              ]
            },
            {
              "text": "Какие типы загрязнения земли существуют?",
              "difficulty": 2,
              "isMultipleChoice": true,
              "answers": [
                { "text": "Химическое", "isCorrect": true },
                { "text": "Радиационное", "isCorrect": true },
                { "text": "Биологическое и механическое", "isCorrect": true },
                { "text": "Только химическое", "isCorrect": false }
              ]
            },
            {
              "text": "Что такое защитная зона согласно ст. 95 ЗК РФ?",
              "difficulty": 1,
              "isMultipleChoice": false,
              "answers": [
                { "text": "Полоса земли с ограниченным использованием", "isCorrect": true },
                { "text": "Участок без ограничений", "isCorrect": false },
                { "text": "Только вокруг водоёмов", "isCorrect": false }
              ]
            },
            {
              "text": "Какие виды защитных зон устанавливаются согласно законодательству?",
              "difficulty": 2,
              "isMultipleChoice": true,
              "answers": [
                { "text": "Около промышленных объектов", "isCorrect": true },
                { "text": "Санитарные зоны водных объектов", "isCorrect": true },
                { "text": "Около ЛЭП и коммуникаций", "isCorrect": true },
                { "text": "Вокруг каждого дома", "isCorrect": false }
              ]
            },
            {
              "text": "Что такое мелиорация земель согласно ст. 79 ЗК РФ?",
              "difficulty": 1,
              "isMultipleChoice": false,
              "answers": [
                { "text": "Улучшение земель путём инженерных работ", "isCorrect": true },
                { "text": "Загрязнение земли", "isCorrect": false },
                { "text": "Продажа участка", "isCorrect": false }
              ]
            },
            {
              "text": "Что входит в рекультивацию земель согласно ст. 67 ЗК РФ?",
              "difficulty": 2,
              "isMultipleChoice": true,
              "answers": [
                { "text": "Восстановление плодородия", "isCorrect": true },
                { "text": "Формирование нового ландшафта", "isCorrect": true },
                { "text": "Посадка растительности", "isCorrect": true },
                { "text": "Только уборка территории", "isCorrect": false }
              ]
            },
            {
              "text": "Какой минимальный размер санитарной зоны у водных объектов?",
              "difficulty": 2,
              "isMultipleChoice": false,
              "answers": [
                { "text": "50-100 метров от берега", "isCorrect": true },
                { "text": "10 метров", "isCorrect": false },
                { "text": "Не устанавливается", "isCorrect": false }
              ]
            },
            {
              "text": "Какая ответственность установлена за загрязнение земли согласно ст. 254 ЗК РФ?",
              "difficulty": 2,
              "isMultipleChoice": true,
              "answers": [
                { "text": "Административная", "isCorrect": true },
                { "text": "Уголовная", "isCorrect": true },
                { "text": "Гражданская", "isCorrect": true },
                { "text": "Только замечание", "isCorrect": false }
              ]
            },
            {
              "text": "Какие штрафы устанавливаются за нарушения природопользования по КоАП РФ?",
              "difficulty": 2,
              "isMultipleChoice": false,
              "answers": [
                { "text": "От 1,000 до 100,000 рублей", "isCorrect": true },
                { "text": "Только предупреждение", "isCorrect": false },
                { "text": "Штрафов не установлено", "isCorrect": false }
              ]
            },
            {
              "text": "Кто обязан проводить рекультивацию нарушенных земель?",
              "difficulty": 2,
              "isMultipleChoice": false,
              "answers": [
                { "text": "Лицо, нарушившее землю (добыча, строительство)", "isCorrect": true },
                { "text": "Только государство", "isCorrect": false },
                { "text": "Соседи участка", "isCorrect": false }
              ]
            }
          ]
        }
      },
      {
        "name": "Государственный контроль и управление землёй",
        "lectures": [
          {
            "title": "Органы управления земельными ресурсами",
            "content": "### Иерархия управления\n\nУправление земельными ресурсами в РФ осуществляется на **трёх уровнях**:\n\n#### 1. Федеральный уровень\n- **Минпромторг** и **Минприроды** — управление федеральными землями\n- **Россельхоз** — сельскохозяйственные земли\n- **Рослесхоз** — лесной фонд\n- **Роспотребнадзор** — санитарно-эпидемиологический контроль\n\n#### 2. Региональный уровень\n- Администрация субъекта РФ\n- Министерства окружающей среды субъектов\n- Региональные органы управления лесами\n\n#### 3. Муниципальный уровень (ст. 60 ЗК РФ)\n- Администрация муниципального образования\n- Органы местного самоуправления\n- Контроль за использованием земель в границах поселения\n\n### Функции органов управления\n\n1. **Планирование** — составление генеральных планов\n2. **Зонирование** — разделение на зоны с ВРИ\n3. **Контроль** — проверка соблюдения законодательства\n4. **Прием жалоб** — разрешение споров\n5. **Выдача разрешений** — на строительство, использование",
            "test": {
              "title": "Тест: Органы управления",
              "timeLimit": 90,
              "questions": [
                {
                  "text": "На скольких уровнях осуществляется управление земельными ресурсами в РФ?",
                  "difficulty": 1,
                  "isMultipleChoice": false,
                  "answers": [
                    { "text": "На трёх уровнях: федеральном, региональном и муниципальном", "isCorrect": true },
                    { "text": "Только на федеральном", "isCorrect": false },
                    { "text": "На двух уровнях", "isCorrect": false }
                  ]
                },
                {
                  "text": "Какие органы входят в федеральный уровень управления земельными ресурсами?",
                  "difficulty": 2,
                  "isMultipleChoice": true,
                  "answers": [
                    { "text": "Минпромторг и Минприроды", "isCorrect": true },
                    { "text": "Россельхоз", "isCorrect": true },
                    { "text": "Рослесхоз", "isCorrect": true },
                    { "text": "Администрация города", "isCorrect": false }
                  ]
                },
                {
                  "text": "Какие функции выполняют органы местного самоуправления согласно ст. 60 ЗК РФ?",
                  "difficulty": 2,
                  "isMultipleChoice": true,
                  "answers": [
                    { "text": "Контроль за использованием земель", "isCorrect": true },
                    { "text": "Принятие генерального плана", "isCorrect": true },
                    { "text": "Выдача разрешений на строительство", "isCorrect": true },
                    { "text": "Федеральное управление лесами", "isCorrect": false }
                  ]
                }
              ]
            }
          },
          {
            "title": "Земельный контроль и надзор",
            "content": "### Виды контроля\n\nСогласно **ст. 71 ЗК РФ**, земельный контроль подразделяется на:\n\n#### 1. Государственный земельный контроль\n- Проверка соблюдения земельного законодательства\n- Органы: органы Роскомзема, администрация субъектов\n- Периодические проверки (кадастровые съёмки)\n- Проверка актуальности сведений в ЕГРН\n\n#### 2. Муниципальный контроль\n- Органы местного самоуправления\n- Контроль в границах поселения\n- Проверка целевого использования\n- Контроль за состоянием земель\n\n#### 3. Общественный контроль\n- Граждане и общественные организации\n- Право на жалобу\n- Право на участие в публичных слушаниях\n- Право на информацию о земельных сделках (ст. 49 ЗК РФ)\n\n### Санкции за нарушения\n\n- **Административное наказание** (КоАП РФ)\n- **Уголовное наказание** (УК РФ)\n- **Гражданское взыскание** (возмещение убытков)\n- **Прекращение прав** на использование земли",
            "test": {
              "title": "Тест: Земельный контроль",
              "timeLimit": 90,
              "questions": [
                {
                  "text": "Какие виды земельного контроля выделяет ст. 71 ЗК РФ?",
                  "difficulty": 1,
                  "isMultipleChoice": true,
                  "answers": [
                    { "text": "Государственный", "isCorrect": true },
                    { "text": "Муниципальный", "isCorrect": true },
                    { "text": "Общественный", "isCorrect": true },
                    { "text": "Только частный", "isCorrect": false }
                  ]
                },
                {
                  "text": "Что проверяют органы государственного земельного контроля?",
                  "difficulty": 2,
                  "isMultipleChoice": true,
                  "answers": [
                    { "text": "Соблюдение земельного законодательства", "isCorrect": true },
                    { "text": "Актуальность сведений в ЕГРН", "isCorrect": true },
                    { "text": "Целевое использование земель", "isCorrect": true },
                    { "text": "Личное отношение к соседям", "isCorrect": false }
                  ]
                },
                {
                  "text": "Какие права имеет общественность при земельном контроле согласно ст. 49 ЗК РФ?",
                  "difficulty": 2,
                  "isMultipleChoice": true,
                  "answers": [
                    { "text": "Право на информацию о земельных сделках", "isCorrect": true },
                    { "text": "Право на жалобу", "isCorrect": true },
                    { "text": "Право на участие в публичных слушаниях", "isCorrect": true },
                    { "text": "Право на запрет сделок", "isCorrect": false }
                  ]
                }
              ]
            }
          },
          {
            "title": "Государственная кадастровая оценка земли",
            "content": "### Определение кадастровой оценки\n\nКадастровая оценка земли согласно **ст. 66 ЗК РФ и ФЗ 'О государственной кадастровой оценке'** — это **определённая в денежном выражении стоимость участка** для целей налогообложения и сбора платежей.\n\n### Методология оценки\n\n1. **Сравнительный подход**\n   - Сравнение с аналогичными участками\n   - Анализ цен продаж\n\n2. **Доходный подход**\n   - Расчёт на основе доходов от участка\n   - Применяется редко для земли\n\n3. **Затратный подход**\n   - На основе затрат на восстановление\n\n### Использование кадастровой оценки\n\n- **Земельный налог** (ст. 391 НК РФ)\n- **Арендные платежи** (ст. 33 ЗК РФ)\n- **Компенсация при изъятии**\n- **Ипотечная оценка**\n\n### Оспаривание оценки\n\nСогласно **ст. 23-24 ФЗ об оценке**, собственник может:\n- Подать жалобу комиссии\n- Оспорить в суде\n- Заказать независимую оценку",
            "test": {
              "title": "Тест: Кадастровая оценка",
              "timeLimit": 90,
              "questions": [
                {
                  "text": "Что такое государственная кадастровая оценка земли согласно ст. 66 ЗК РФ?",
                  "difficulty": 1,
                  "isMultipleChoice": false,
                  "answers": [
                    { "text": "Определённая в денежном выражении стоимость участка для целей налогообложения", "isCorrect": true },
                    { "text": "Только площадь участка", "isCorrect": false },
                    { "text": "Местоположение участка", "isCorrect": false }
                  ]
                },
                {
                  "text": "Какие методы используются при кадастровой оценке земли?",
                  "difficulty": 2,
                  "isMultipleChoice": true,
                  "answers": [
                    { "text": "Сравнительный подход", "isCorrect": true },
                    { "text": "Доходный подход", "isCorrect": true },
                    { "text": "Затратный подход", "isCorrect": true },
                    { "text": "Только рыночная цена", "isCorrect": false }
                  ]
                },
                {
                  "text": "Для каких целей используется кадастровая оценка?",
                  "difficulty": 2,
                  "isMultipleChoice": true,
                  "answers": [
                    { "text": "Земельный налог", "isCorrect": true },
                    { "text": "Расчёт арендной платы", "isCorrect": true },
                    { "text": "Компенсация при изъятии", "isCorrect": true },
                    { "text": "Только для информации", "isCorrect": false }
                  ]
                }
              ]
            }
          }
        ],
        "test": {
          "title": "Итоговый тест: Государственное управление",
          "timeLimit": 420,
          "questions": [
            {
              "text": "На скольких уровнях осуществляется управление земельными ресурсами?",
              "difficulty": 1,
              "isMultipleChoice": false,
              "answers": [
                { "text": "На трёх: федеральном, региональном и муниципальном", "isCorrect": true },
                { "text": "Только на федеральном", "isCorrect": false },
                { "text": "На местном уровне", "isCorrect": false }
              ]
            },
            {
              "text": "Какие органы входят в федеральный уровень управления?",
              "difficulty": 2,
              "isMultipleChoice": true,
              "answers": [
                { "text": "Минпромторг, Минприроды, Россельхоз, Рослесхоз", "isCorrect": true },
                { "text": "Администрация муниципалитета", "isCorrect": false },
                { "text": "Органы местного самоуправления", "isCorrect": false }
              ]
            },
            {
              "text": "Какие виды земельного контроля существуют согласно ст. 71 ЗК РФ?",
              "difficulty": 1,
              "isMultipleChoice": true,
              "answers": [
                { "text": "Государственный", "isCorrect": true },
                { "text": "Муниципальный", "isCorrect": true },
                { "text": "Общественный", "isCorrect": true },
                { "text": "Только частный", "isCorrect": false }
              ]
            },
            {
              "text": "Что проверяет государственный земельный контроль?",
              "difficulty": 2,
              "isMultipleChoice": true,
              "answers": [
                { "text": "Соблюдение земельного законодательства", "isCorrect": true },
                { "text": "Актуальность сведений в ЕГРН", "isCorrect": true },
                { "text": "Целевое использование земель", "isCorrect": true },
                { "text": "Личные отношения граждан", "isCorrect": false }
              ]
            },
            {
              "text": "Какие права имеет граждане при земельном контроле согласно ст. 49 ЗК РФ?",
              "difficulty": 2,
              "isMultipleChoice": true,
              "answers": [
                { "text": "Право на информацию", "isCorrect": true },
                { "text": "Право на жалобу", "isCorrect": true },
                { "text": "Право на участие в слушаниях", "isCorrect": true },
                { "text": "Право на запрет земельных сделок", "isCorrect": false }
              ]
            },
            {
              "text": "Что такое государственная кадастровая оценка земли согласно ст. 66 ЗК РФ?",
              "difficulty": 1,
              "isMultipleChoice": false,
              "answers": [
                { "text": "Денежное выражение стоимости участка для налогообложения", "isCorrect": true },
                { "text": "Только площадь участка", "isCorrect": false },
                { "text": "Адрес участка", "isCorrect": false }
              ]
            },
            {
              "text": "Какие методы используются при кадастровой оценке?",
              "difficulty": 2,
              "isMultipleChoice": true,
              "answers": [
                { "text": "Сравнительный подход", "isCorrect": true },
                { "text": "Доходный подход", "isCorrect": true },
                { "text": "Затратный подход", "isCorrect": true },
                { "text": "Только опрос соседей", "isCorrect": false }
              ]
            },
            {
              "text": "Для каких целей используется кадастровая оценка?",
              "difficulty": 2,
              "isMultipleChoice": true,
              "answers": [
                { "text": "Земельный налог", "isCorrect": true },
                { "text": "Расчёт арендной платы", "isCorrect": true },
                { "text": "Компенсация при изъятии", "isCorrect": true },
                { "text": "Только для информации", "isCorrect": false }
              ]
            },
            {
              "text": "Может ли собственник оспорить кадастровую оценку?",
              "difficulty": 2,
              "isMultipleChoice": false,
              "answers": [
                { "text": "Да, подав жалобу или обратившись в суд согласно ст. 23-24 ФЗ об оценке", "isCorrect": true },
                { "text": "Нет, оценка неоспорима", "isCorrect": false },
                { "text": "Только в исключительных случаях", "isCorrect": false }
              ]
            },
            {
              "text": "Какие функции выполняют органы муниципального управления согласно ст. 60 ЗК РФ?",
              "difficulty": 2,
              "isMultipleChoice": true,
              "answers": [
                { "text": "Контроль за использованием земель", "isCorrect": true },
                { "text": "Принятие генерального плана", "isCorrect": true },
                { "text": "Выдача разрешений на строительство", "isCorrect": true },
                { "text": "Управление федеральными землями", "isCorrect": false }
              ]
            }
          ]
        }
      },
      {
        "name": "Земельные споры и их разрешение",
        "lectures": [
          {
            "title": "Виды земельных споров",
            "content": "### Классификация земельных споров\n\nСогласно **ст. 64 ЗК РФ**, земельные споры подразделяются на:\n\n#### 1. Споры о праве собственности\n- Истребование участка (виндикация)\n- Признание права собственности\n- Оспаривание регистрации прав\n\n#### 2. Споры об ограничениях в использовании\n- Оспаривание зонирования\n- Оспаривание сервитутов\n- Споры о защитных зонах\n\n#### 3. Соседские споры\n- Нарушение границ\n- Отвод сточных вод\n- Затенение участка\n- Загрязнение соседней земли\n\n#### 4. Споры о возмещении убытков\n- При загрязнении\n- При нарушении использования\n- При незаконном занятии\n\n#### 5. Споры о налогообложении\n- Размер земельного налога\n- Кадастровая оценка\n- Льготы и преференции",
            "test": {
              "title": "Тест: Виды споров",
              "timeLimit": 90,
              "questions": [
                {
                  "text": "Какие основные виды земельных споров выделяет ст. 64 ЗК РФ?",
                  "difficulty": 1,
                  "isMultipleChoice": true,
                  "answers": [
                    { "text": "Споры о праве собственности", "isCorrect": true },
                    { "text": "Споры об ограничениях в использовании", "isCorrect": true },
                    { "text": "Соседские споры", "isCorrect": true },
                    { "text": "Только наследственные споры", "isCorrect": false }
                  ]
                },
                {
                  "text": "Какие вопросы включают соседские земельные споры?",
                  "difficulty": 2,
                  "isMultipleChoice": true,
                  "answers": [
                    { "text": "Нарушение границ", "isCorrect": true },
                    { "text": "Отвод сточных вод", "isCorrect": true },
                    { "text": "Загрязнение соседней земли", "isCorrect": true },
                    { "text": "Выбор культур для посева", "isCorrect": false }
                  ]
                },
                {
                  "text": "На какие категории делятся споры о налогообложении?",
                  "difficulty": 2,
                  "isMultipleChoice": true,
                  "answers": [
                    { "text": "Размер земельного налога", "isCorrect": true },
                    { "text": "Кадастровая оценка", "isCorrect": true },
                    { "text": "Льготы и преференции", "isCorrect": true },
                    { "text": "Только размер налога", "isCorrect": false }
                  ]
                }
              ]
            }
          },
          {
            "title": "Претензионный порядок разрешения",
            "content": "### Досудебный порядок\n\nПеред обращением в суд согласно **ст. 56 ГПК РФ** следует направить **претензию**:\n\n#### Форма претензии\n- Письменный документ\n- На официальном бланке\n- С указанием сути спора\n- С требованиями истца\n- С документами-приложениями\n\n#### Содержание претензии\n1. **Фактические обстоятельства** (что произошло)\n2. **Нормативная база** (какие законы нарушены)\n3. **Требования** (что просит истец)\n4. **Сумма требований** (в рублях)\n5. **Сроки** (на ответ — обычно 30 дней)\n\n#### Сроки рассмотрения\n- Ответчик должен ответить на претензию в течение **30 дней**\n- Возможна переписка перед судом\n- Проводятся переговоры\n\n#### Результаты\n- **Согласие** — спор разрешён\n- **Отказ** — право на судебное разбирательство\n- **Молчание** — считается отказом",
            "test": {
              "title": "Тест: Претензионный порядок",
              "timeLimit": 90,
              "questions": [
                {
                  "text": "Что такое претензия согласно ст. 56 ГПК РФ?",
                  "difficulty": 1,
                  "isMultipleChoice": false,
                  "answers": [
                    { "text": "Письменное требование до обращения в суд", "isCorrect": true },
                    { "text": "Судебный документ", "isCorrect": false },
                    { "text": "Письмо без требований", "isCorrect": false }
                  ]
                },
                {
                  "text": "Какие элементы должны быть в претензии?",
                  "difficulty": 2,
                  "isMultipleChoice": true,
                  "answers": [
                    { "text": "Фактические обстоятельства", "isCorrect": true },
                    { "text": "Нормативная база", "isCorrect": true },
                    { "text": "Требования и сумма", "isCorrect": true },
                    { "text": "Только грубые требования", "isCorrect": false }
                  ]
                },
                {
                  "text": "Сколько дней даётся на ответ на претензию?",
                  "difficulty": 1,
                  "isMultipleChoice": false,
                  "answers": [
                    { "text": "30 дней", "isCorrect": true },
                    { "text": "7 дней", "isCorrect": false },
                    { "text": "60 дней", "isCorrect": false }
                  ]
                }
              ]
            }
          },
          {
            "title": "Судебный порядок разрешения земельных споров",
            "content": "### Компетенция судов\n\nСогласно **ст. 126-127 ГПК РФ**, земельные споры рассматриваются:\n\n#### Мировой суд\n- Споры о сумме до **100,000 рублей**\n- Простые соседские споры\n- Конфликты о границах\n\n#### Районный суд\n- Споры от **100,000 до нескольких млн**\n- Сложные споры о собственности\n- Споры о восстановлении прав\n\n#### Апелляционный суд\n- Пересмотр решений районных судов\n- На новые доказательства\n- На неправильное применение закона\n\n#### Кассационный суд\n- Пересмотр по поводу нарушений процедуры\n- На вопросы права\n\n### Особенности земельных разбирательств\n\n1. **Сроки рассмотрения** — обычно 2-3 месяца\n2. **Доказательства** — кадастровые планы, свидетельства о праве\n3. **Экспертизы** — землеустроительная, техническая\n4. **Третьи лица** — соседи, органы управления\n5. **Исполнение решений** — судебный пристав",
            "test": {
              "title": "Тест: Судебный порядок",
              "timeLimit": 90,
              "questions": [
                {
                  "text": "Какой суд рассматривает земельные споры до 100,000 рублей согласно ст. 126 ГПК РФ?",
                  "difficulty": 1,
                  "isMultipleChoice": false,
                  "answers": [
                    { "text": "Мировой суд", "isCorrect": true },
                    { "text": "Районный суд", "isCorrect": false },
                    { "text": "Апелляционный суд", "isCorrect": false }
                  ]
                },
                {
                  "text": "Какой суд рассматривает сложные земельные споры о собственности?",
                  "difficulty": 1,
                  "isMultipleChoice": false,
                  "answers": [
                    { "text": "Районный суд", "isCorrect": true },
                    { "text": "Мировой суд", "isCorrect": false },
                    { "text": "Апелляционный суд", "isCorrect": false }
                  ]
                },
                {
                  "text": "Какие документы используются как доказательства в земельных спорах?",
                  "difficulty": 2,
                  "isMultipleChoice": true,
                  "answers": [
                    { "text": "Кадастровые планы", "isCorrect": true },
                    { "text": "Свидетельства о праве", "isCorrect": true },
                    { "text": "Выписки из ЕГРН", "isCorrect": true },
                    { "text": "Только устные показания", "isCorrect": false }
                  ]
                }
              ]
            }
          },
          {
            "title": "Альтернативные способы разрешения земельных споров",
            "content": "### Внесудебные методы\n\nСогласно **ст. 11 ГПК РФ**, земельные споры могут разрешаться:\n\n#### 1. Третейский суд (арбитраж)\n- Созданный по соглашению сторон\n- Рассматривает споры на основе арбитражного регламента\n- Решение обязательно (но может быть обжаловано)\n- Затраты ниже, чем в государственном суде\n\n#### 2. Медиация\n- Переговоры с участием нейтрального посредника\n- Медиатор помогает найти взаимоприемлемое решение\n- Стороны остаются в контроле\n- Соглашение имеет силу договора\n\n#### 3. Переговоры\n- Прямые переговоры между сторонами\n- Может быть на основе претензии\n- Часто результативно при соседских конфликтах\n- Требует готовности к компромиссу\n\n#### 4. Административный порядок\n- Обращение в органы управления\n- Для споров о целевом использовании\n- Для нарушений зонирования\n- Орган принимает решение (может быть обжаловано в суд)",
            "test": {
              "title": "Тест: Альтернативные способы",
              "timeLimit": 90,
              "questions": [
                {
                  "text": "Какие альтернативные способы разрешения земельных споров предусмотрены ст. 11 ГПК РФ?",
                  "difficulty": 1,
                  "isMultipleChoice": true,
                  "answers": [
                    { "text": "Третейский суд", "isCorrect": true },
                    { "text": "Медиация", "isCorrect": true },
                    { "text": "Переговоры", "isCorrect": true },
                    { "text": "Только судебный порядок", "isCorrect": false }
                  ]
                },
                {
                  "text": "Что такое третейский суд в земельных спорах?",
                  "difficulty": 2,
                  "isMultipleChoice": false,
                  "answers": [
                    { "text": "Суд, созданный по соглашению сторон для разрешения спора", "isCorrect": true },
                    { "text": "Государственный суд", "isCorrect": false },
                    { "text": "Только органы управления", "isCorrect": false }
                  ]
                },
                {
                  "text": "Какие преимущества имеет медиация при разрешении земельных споров?",
                  "difficulty": 2,
                  "isMultipleChoice": true,
                  "answers": [
                    { "text": "Стороны сохраняют контроль", "isCorrect": true },
                    { "text": "Возможен взаимоприемлемый результат", "isCorrect": true },
                    { "text": "Быстрее, чем суд", "isCorrect": true },
                    { "text": "Всегда обязательна для исполнения", "isCorrect": false }
                  ]
                }
              ]
            }
          }
        ],
        "test": {
          "title": "Итоговый тест: Земельные споры",
          "timeLimit": 420,
          "questions": [
            {
              "text": "Какие основные виды земельных споров выделяет ст. 64 ЗК РФ?",
              "difficulty": 1,
              "isMultipleChoice": true,
              "answers": [
                { "text": "Споры о праве собственности", "isCorrect": true },
                { "text": "Соседские споры", "isCorrect": true },
                { "text": "Споры об ограничениях в использовании", "isCorrect": true },
                { "text": "Только наследственные споры", "isCorrect": false }
              ]
            },
            {
              "text": "Что такое претензия согласно ст. 56 ГПК РФ?",
              "difficulty": 1,
              "isMultipleChoice": false,
              "answers": [
                { "text": "Письменное требование до обращения в суд", "isCorrect": true },
                { "text": "Судебное решение", "isCorrect": false },
                { "text": "Жалоба на решение суда", "isCorrect": false }
              ]
            },
            {
              "text": "Сколько дней даётся на ответ на претензию?",
              "difficulty": 1,
              "isMultipleChoice": false,
              "answers": [
                { "text": "30 дней", "isCorrect": true },
                { "text": "7 дней", "isCorrect": false },
                { "text": "60 дней", "isCorrect": false }
              ]
            },
            {
              "text": "Какой суд рассматривает земельные споры до 100,000 рублей?",
              "difficulty": 1,
              "isMultipleChoice": false,
              "answers": [
                { "text": "Мировой суд согласно ст. 126 ГПК РФ", "isCorrect": true },
                { "text": "Районный суд", "isCorrect": false },
                { "text": "Апелляционный суд", "isCorrect": false }
              ]
            },
            {
              "text": "Какие документы используются как доказательства в земельных спорах?",
              "difficulty": 2,
              "isMultipleChoice": true,
              "answers": [
                { "text": "Кадастровые планы", "isCorrect": true },
                { "text": "Свидетельства о праве", "isCorrect": true },
                { "text": "Выписки из ЕГРН", "isCorrect": true },
                { "text": "Только устные показания", "isCorrect": false }
              ]
            },
            {
              "text": "Какие альтернативные способы разрешения земельных споров существуют согласно ст. 11 ГПК РФ?",
              "difficulty": 2,
              "isMultipleChoice": true,
              "answers": [
                { "text": "Третейский суд", "isCorrect": true },
                { "text": "Медиация", "isCorrect": true },
                { "text": "Переговоры и административный порядок", "isCorrect": true },
                { "text": "Только судебный порядок", "isCorrect": false }
              ]
            },
            {
              "text": "Что такое третейский суд в земельных спорах?",
              "difficulty": 2,
              "isMultipleChoice": false,
              "answers": [
                { "text": "Суд, созданный по соглашению сторон", "isCorrect": true },
                { "text": "Государственный суд", "isCorrect": false },
                { "text": "Орган управления", "isCorrect": false }
              ]
            },
            {
              "text": "Какие соседские конфликты входят в категорию земельных споров?",
              "difficulty": 2,
              "isMultipleChoice": true,
              "answers": [
                { "text": "Нарушение границ", "isCorrect": true },
                { "text": "Отвод сточных вод", "isCorrect": true },
                { "text": "Загрязнение соседней земли", "isCorrect": true },
                { "text": "Только о размере участков", "isCorrect": false }
              ]
            },
            {
              "text": "Какие преимущества имеет медиация при разрешении земельных споров?",
              "difficulty": 2,
              "isMultipleChoice": true,
              "answers": [
                { "text": "Быстрее и дешевле, чем суд", "isCorrect": true },
                { "text": "Стороны сохраняют контроль", "isCorrect": true },
                { "text": "Возможен взаимоприемлемый результат", "isCorrect": true },
                { "text": "Результат всегда обязателен", "isCorrect": false }
              ]
            },
            {
              "text": "Сколько примерно времени занимает рассмотрение земельного спора в суде?",
              "difficulty": 1,
              "isMultipleChoice": false,
              "answers": [
                { "text": "2-3 месяца обычно", "isCorrect": true },
                { "text": "1 неделя", "isCorrect": false },
                { "text": "6 месяцев всегда", "isCorrect": false }
              ]
            }
          ]
        }
      }
    ]
  }
]